rq_dashboard/__init__.py
rq_dashboard/__main__.py
rq_dashboard/cli.py
rq_dashboard/default_settings.py
rq_dashboard/legacy_config.py
rq_dashboard/version.py
rq_dashboard/web.py
rq_dashboard/static/favicon.ico
rq_dashboard/static/css/bootstrap.css
rq_dashboard/static/css/bootstrap.min.css
rq_dashboard/static/css/main.css
rq_dashboard/static/js/bootstrap.bundle.js
rq_dashboard/static/js/bootstrap.bundle.min.js
rq_dashboard/static/js/jquery-3.4.1.min.js
rq_dashboard/static/js/sugar-1.2.1.min.js
rq_dashboard/static/js/underscore-umd-min.js
rq_dashboard/templates/rq_dashboard/base.html
rq_dashboard/templates/rq_dashboard/footer.html
rq_dashboard/templates/rq_dashboard/inline_js.html
rq_dashboard/templates/rq_dashboard/job.html
rq_dashboard/templates/rq_dashboard/jobs.html
rq_dashboard/templates/rq_dashboard/navbar.html
rq_dashboard/templates/rq_dashboard/queues.html
rq_dashboard/templates/rq_dashboard/workers.html
rq_dashboard/templates/rq_dashboard/scripts/dashboard.js
rq_dashboard/templates/rq_dashboard/scripts/job.js
rq_dashboard/templates/rq_dashboard/scripts/jobs.js
rq_dashboard/templates/rq_dashboard/scripts/queues.js
rq_dashboard/templates/rq_dashboard/scripts/workers.js
rq_dashboard-0.8.4.dist-info/licenses/AUTHORS
rq_dashboard-0.8.4.dist-info/licenses/LICENSE
tests/fixtures/__init__.py
tests/fixtures/rq_1_0.py
rq_dashboard-0.8.4.dist-info/METADATA
rq_dashboard-0.8.4.dist-info/WHEEL
rq_dashboard-0.8.4.dist-info/entry_points.txt
rq_dashboard-0.8.4.dist-info/top_level.txt
rq_dashboard-0.8.4.dist-info/RECORD
