Metadata-Version: 2.4
Name: rq-dashboard
Version: 0.8.4
Summary: rq-dashboard is a general purpose, lightweight, web interface to monitor your RQ queues, jobs, and workers in realtime.
Home-page: https://github.com/Parallels/rq-dashboard
Author: Vincent Driessen
Author-email: vincent@3rdcloud.com
License: BSD
Platform: any
Classifier: Development Status :: 4 - Beta
Classifier: Intended Audience :: Developers
Classifier: Intended Audience :: End Users/Desktop
Classifier: Intended Audience :: Information Technology
Classifier: Intended Audience :: Science/Research
Classifier: Intended Audience :: System Administrators
Classifier: License :: OSI Approved :: BSD License
Classifier: Operating System :: POSIX
Classifier: Operating System :: MacOS
Classifier: Operating System :: Unix
Classifier: Programming Language :: Python
Classifier: Programming Language :: Python :: 3
Classifier: Programming Language :: Python :: 3.5
Classifier: Programming Language :: Python :: 3.6
Classifier: Programming Language :: Python :: 3.7
Classifier: Topic :: Software Development :: Libraries :: Python Modules
Classifier: Topic :: Internet
Classifier: Topic :: Scientific/Engineering
Classifier: Topic :: System :: Distributed Computing
Classifier: Topic :: System :: Systems Administration
Classifier: Topic :: System :: Monitoring
License-File: LICENSE
License-File: AUTHORS
Requires-Dist: rq>=1.0
Requires-Dist: Flask
Requires-Dist: redis
Requires-Dist: arrow
Requires-Dist: redis-sentinel-url
Dynamic: author
Dynamic: author-email
Dynamic: classifier
Dynamic: description
Dynamic: description-content-type
Dynamic: home-page
Dynamic: license
Dynamic: license-file
Dynamic: platform
Dynamic: requires-dist
Dynamic: summary
